netcdf4_soft_links
