Metadata-Version: 1.1
Name: netcdf4-soft-links
Version: 0.7.8.4
Summary: Tools to create soft links to netcdf4 files.
Home-page: UNKNOWN
Author: F. B. Laliberte P. J. Kushner
Author-email: frederic.laliberte@utoronto.ca
License: BSD
Keywords: atmosphere climate
Platform: UNKNOWN
Classifier: Development Status :: 4 - Beta
Classifier: Intended Audience :: Science/Research
Classifier: Natural Language :: English
Classifier: License :: OSI Approved :: BSD License
Classifier: Programming Language :: Python :: 2.7
Classifier: Programming Language :: Fortran
Classifier: Topic :: Scientific/Engineering :: Mathematics
